[{"line":1,"elements":[{"start_timestamp":"2022-04-12T08:56:05.075Z","line":8,"name":"API ile hava durumu tahmini alma","description":"","id":"hava-durumu-api-si-kullanarak-parametre-olarak-verilen-sehir-ve-gün-bilgilerine-uygun-hava-durumunu-alma;apı-ile-hava-durumu-tahmini-alma;;2","type":"scenario","keyword":"Scenario Outline","steps":[{"result":{"duration":1247787600,"status":"passed"},"line":4,"name":"\"edirne\" 32 bilgilerine göre request atildiginda","match":{"arguments":[{"val":"\"edirne\"","offset":0},{"val":"32","offset":9}],"location":"StepDefination.GET_Request.bilgilerine_göre_request_atildiginda(java.lang.String,java.lang.Integer)"},"keyword":"When "},{"result":{"status":"passed"},"line":5,"name":"Dort gunluk hava durumu tahmini gelmis olmalidir","match":{"location":"StepDefination.GET_Request.dort_gunluk_hava_durumu_tahmini_gelmis_olmalidir()"},"keyword":"Then "}]},{"start_timestamp":"2022-04-12T08:56:06.518Z","line":17,"name":"Google'dan sehre ve gune uygun hava durumu bilgisini alma","description":"","id":"hava-durumu-api-si-kullanarak-parametre-olarak-verilen-sehir-ve-gün-bilgilerine-uygun-hava-durumunu-alma;google-dan-sehre-ve-gune-uygun-hava-durumu-bilgisini-alma;;2","type":"scenario","keyword":"Scenario Outline","steps":[{"result":{"duration":5232274800,"status":"passed"},"line":11,"name":"google.com sitesine gidilmis olmalidir","match":{"location":"StepDefination.GET_Request.google_com_sitesine_gidilmis_olmalidir()"},"keyword":"Given "},{"result":{"duration":3962802300,"status":"passed"},"line":12,"name":"Arama kismina \"edirne\" hava durumu yazildigi zaman","match":{"arguments":[{"val":"\"edirne\"","offset":14}],"location":"StepDefination.GET_Request.arama_kismina_hava_durumu_yazildigi_zaman(java.lang.String)"},"keyword":"When "},{"result":{"duration":130088500,"status":"passed"},"line":13,"name":"4. gunun hava durumuna bakildiginda","match":{"arguments":[{"val":"4","offset":0}],"location":"StepDefination.GET_Request.gunun_hava_durumuna_bakildiginda(java.lang.Integer)"},"keyword":"And "},{"result":{"duration":109075400,"status":"passed"},"line":14,"name":"Uygun hava durumu gelmis olmalidir","match":{"location":"StepDefination.GET_Request.uygun_hava_durumu_gelmis_olmalidir()"},"keyword":"Then "}]}],"name":"Hava durumu Api'si kullanarak parametre olarak verilen sehir ve gün bilgilerine uygun hava durumunu alma","description":"","id":"hava-durumu-api-si-kullanarak-parametre-olarak-verilen-sehir-ve-gün-bilgilerine-uygun-hava-durumunu-alma","keyword":"Feature","uri":"file:src/test/resources/Features/WeatherAPI.feature","tags":[]}]